setup.py
pydo/List.py
pydo/Task.py
pydo/__init__.py
pydo/__main__.py
pydo/conf_parser.py
pydo/config.py
pydo/file_utils.py
pydo/interactions.py
pydo/utils.py
pydolist.egg-info/PKG-INFO
pydolist.egg-info/SOURCES.txt
pydolist.egg-info/dependency_links.txt
pydolist.egg-info/entry_points.txt
pydolist.egg-info/not-zip-safe
pydolist.egg-info/top_level.txt