Metadata-Version: 1.0
Name: pydolist
Version: 1.0.2
Summary: A simple terminal TODO app written in Python 3.
Home-page: https://github.com/rugglcon/pydolist
Author: Connor Ruggles
Author-email: conruggles@gmail.com
License: GPLv3
Platform: UNKNOWN
